cli/__init__.py
cli/orchai.py
core/__init__.py
core/analyzer.py
core/docker_commands.py
core/generator.py
core/llm.py
core/prompts.py
orchai-1.0.0.dist-info/licenses/LICENSE
orchai-1.0.0.dist-info/METADATA
orchai-1.0.0.dist-info/WHEEL
orchai-1.0.0.dist-info/entry_points.txt
orchai-1.0.0.dist-info/top_level.txt
orchai-1.0.0.dist-info/RECORD
